{
    "editor": [{
        "identifier": "SELECTOR",
        "controlType": "SECTION",
        "children": [{
            "controlType": "DROP_DOWN",
            "options": [
                {
                    "label": "List Documents",
                    "value": "GET_COLLECTION"
                },
                {
                    "label": "Create document",
                    "value": "CREATE_DOCUMENT"
                },
                {
                    "label": "Update document",
                    "value": "UPDATE_DOCUMENT"
                },
                {
                    "label": "Delete document",
                    "value": "DELETE_DOCUMENT"
                },
                {
                    "label": "Get Document",
                    "value": "GET_DOCUMENT"
                },
                {
                    "label": "Upsert Document",
                    "value": "SET_DOCUMENT"
                },
                {
                    "label": "Add document to collection",
                    "value": "ADD_TO_COLLECTION"
                }
            ],
            "description": "Choose method you would like to use",
            "label": "Command",
            "initialValue": "GET_COLLECTION",
            "configProperty": "actionConfiguration.formData.command.data"
        }]
    }],
    "files": [
        "addToCollection.json",
        "createDocument.json",
        "deleteDocument.json",
        "getCollection.json",
        "getDocument.json",
        "setDocument.json",
        "updateDocument.json"
    ]
}
